doodler_engine/__init__.py
doodler_engine/_version.py
doodler_engine/annotations_to_segmentations.py
doodler_engine/app_funcs.py
doodler_engine/defaults.py
doodler_engine/image_segmentation.py
doodler_engine/plot_utils.py
doodler_engine-0.0.3.dist-info/LICENSE
doodler_engine-0.0.3.dist-info/METADATA
doodler_engine-0.0.3.dist-info/WHEEL
doodler_engine-0.0.3.dist-info/top_level.txt
doodler_engine-0.0.3.dist-info/RECORD
