Metadata-Version: 2.1
Name: doodler-engine
Version: 0.0.3
Summary: Imports into Dash-Doodler and Holo-Doodler labeling programs
Home-page: UNKNOWN
Author: Daniel Buscombe
Author-email: dbuscombe@gmail.email
License: UNKNOWN
Platform: UNKNOWN
Classifier: Programming Language :: Python :: 3
Classifier: License :: OSI Approved :: MIT License
Classifier: Operating System :: OS Independent
Requires-Python: >=3.6
Requires-Dist: versioneer
